PySPIDER/__init__.py
PySPIDER/commons/TInvPower.py
PySPIDER/commons/__init__.py
PySPIDER/commons/identify_models.py
PySPIDER/commons/library.py
PySPIDER/commons/process_library_terms.py
PySPIDER/commons/sparse_reg.py
PySPIDER/commons/sparse_reg_bf.py
PySPIDER/commons/sr_utils.py
PySPIDER/commons/utils.py
PySPIDER/commons/weight.py
PySPIDER/commons/z3base.py
PySPIDER/continuous/__init__.py
PySPIDER/continuous/library.py
PySPIDER/continuous/process_library_terms.py
PySPIDER/discrete/__init__.py
PySPIDER/discrete/coarse_grain_utils.py
PySPIDER/discrete/convolution.py
PySPIDER/discrete/discrete_utils.py
PySPIDER/discrete/interp.py
PySPIDER/discrete/library.py
PySPIDER/discrete/process_library_terms.py
PySPIDER/discrete/read_LAMMPS.py
pyspider_sr-2.1.0.dist-info/METADATA
pyspider_sr-2.1.0.dist-info/WHEEL
pyspider_sr-2.1.0.dist-info/top_level.txt
pyspider_sr-2.1.0.dist-info/RECORD
