Metadata-Version: 2.4
Name: PySPIDER_SR
Version: 2.1.0
Summary: A Python implementation of the SPIDER framework for data-driven equivariant modeling of continuous and discrete systems
Author-email: Daniel Gurevich <nerpa12@gmail.com>
License-Expression: GPL-3.0-or-later
Project-URL: Homepage, https://github.com/sibirica/PySPIDER
Project-URL: Issues, https://github.com/sibirica/PySPIDER/issues
Classifier: Programming Language :: Python :: 3
Classifier: Operating System :: OS Independent
Requires-Python: >=3.12
Requires-Dist: z3-solver
Requires-Dist: findiff
Requires-Dist: numba-kdtree
Requires-Dist: numpy
Requires-Dist: scipy>=1.6
